<?xml version='1.0' encoding='UTF-8'?>

<bag>
 <fileEntry key="5786801242488962731" value="0"/>
 <fileEntry key="5786801250437247134" value="1"/>
 <fileEntry key="5786801259102841452" value="2"/>
 <fileEntry key="5786801267550994254" value="3"/>
 <fileEntry key="5786801276108181195" value="4"/>
 <fileEntry key="5786801284830272571" value="5"/>
 <fileEntry key="5786801293948787274" value="6"/>
 <fileEntry key="5786801303337302421" value="7"/>
 <fileEntry key="5786801313412164844" value="8"/>
 <fileEntry key="5786801323479063575" value="9"/>
 <fileEntry key="5786801334184326929" value="10"/>
 <fileEntry key="5786801344919579521" value="11"/>
 <fileEntry key="5786801356799405551" value="12"/>
 <fileEntry key="5786801370583326425" value="13"/>
 <fileEntry key="5786801386093276228" value="14"/>
</bag>
